{"sections":{"pf-18b83f13":{"type":"pf-18b83f13","disabled":true,"settings":{}},"jas_advanced_content_nytVhK":{"type":"jas-advanced-content","blocks":{"html_XiyrNc":{"type":"html","settings":{"code":"<h1>Safety Data Sheet <\/h1>","width":"12","alignment":"tc"}}},"block_order":["html_XiyrNc"],"custom_css":["h1 {text-align:center}"],"settings":{"section_margin_top":"","section_margin_bottom":"","section_margin_left":"","section_margin_right":"","section_padding_top":"","section_padding_right":"","section_padding_bottom":"","section_padding_left":""}}},"order":["pf-18b83f13","jas_advanced_content_nytVhK"]}